{
  "holidays": [
    {
      "id": "be3c",
      "date": "2025-01-01",
      "name": "New Year Holiday",
      "type": "Public",
      "recurring": false,
      "country_code": "MM",
      "region": "ALL"
    },
    {
      "id": "24aa",
      "date": "2025-01-04",
      "name": "Independence Day",
      "type": "Public",
      "recurring": false,
      "country_code": "MM",
      "region": "ALL"
    },
    {
      "id": "90b0",
      "date": "2025-02-12",
      "name": "Union Day",
      "type": "Public",
      "recurring": false,
      "country_code": "MM",
      "region": "ALL"
    },
    {
      "id": "b873",
      "date": "2025-03-02",
      "name": "Peasants' Day",
      "type": "Public",
      "recurring": false,
      "country_code": "MM",
      "region": "ALL"
    },
    {
      "id": "8682",
      "date": "2025-03-13",
      "name": "Full Moon Day of Tabaung",
      "type": "Public",
      "recurring": false,
      "country_code": "MM",
      "region": "ALL"
    },
    {
      "id": "e389",
      "date": "2025-03-27",
      "name": "Armed Forces' Day",
      "type": "Public",
      "recurring": false,
      "country_code": "MM",
      "region": "ALL"
    },
    {
      "id": "1559",
      "date": "2025-04-13",
      "name": "Mahar Thingyan (Water Festival)",
      "type": "Public",
      "recurring": false,
      "country_code": "MM",
      "region": "ALL"
    },
    {
      "id": "1c14",
      "date": "2025-04-14",
      "name": "Mahar Thingyan (Water Festival)",
      "type": "Public",
      "recurring": false,
      "country_code": "MM",
      "region": "ALL"
    },
    {
      "id": "a365",
      "date": "2025-04-15",
      "name": "Mahar Thingyan (Water Festival)",
      "type": "Public",
      "recurring": false,
      "country_code": "MM",
      "region": "ALL"
    },
    {
      "id": "85c5",
      "date": "2025-04-16",
      "name": "Mahar Thingyan (Water Festival)",
      "type": "Public",
      "recurring": false,
      "country_code": "MM",
      "region": "ALL"
    },
    {
      "id": "938a",
      "date": "2025-04-17",
      "name": "Myanmar New Year",
      "type": "Public",
      "recurring": false,
      "country_code": "MM",
      "region": "ALL"
    },
    {
      "id": "90ce",
      "date": "2025-05-01",
      "name": "International Worker's Day",
      "type": "Public",
      "recurring": false,
      "country_code": "MM",
      "region": "ALL"
    },
    {
      "id": "6996",
      "date": "2025-05-11",
      "name": "Full Moon Day of Kasong",
      "type": "Public",
      "recurring": false,
      "country_code": "MM",
      "region": "ALL"
    },
    {
      "id": "ac92",
      "date": "2025-06-07",
      "name": "Eid al-Adha",
      "type": "Public",
      "recurring": false,
      "country_code": "MM",
      "region": "ALL"
    },
    {
      "id": "09e5",
      "date": "2025-07-09",
      "name": "Full Moon Day of Waso (Beginning of Buddhist Lent)",
      "type": "Public",
      "recurring": false,
      "country_code": "MM",
      "region": "ALL"
    },
    {
      "id": "e2e6",
      "date": "2025-07-19",
      "name": "Martyrs' Day",
      "type": "Public",
      "recurring": false,
      "country_code": "MM",
      "region": "ALL"
    },
    {
      "id": "5422",
      "date": "2025-10-05",
      "name": "Full Moon Day of Thadingyut Holiday (End of Buddhist Lent)",
      "type": "Public",
      "recurring": false,
      "country_code": "MM",
      "region": "ALL"
    },
    {
      "id": "dd4c",
      "date": "2025-10-06",
      "name": "Full Moon Day of Thadingyut Holiday (End of Buddhist Lent)",
      "type": "Public",
      "recurring": false,
      "country_code": "MM",
      "region": "ALL"
    },
    {
      "id": "7d6c",
      "date": "2025-10-07",
      "name": "Full Moon Day of Thadingyut Holiday (End of Buddhist Lent)",
      "type": "Public",
      "recurring": false,
      "country_code": "MM",
      "region": "ALL"
    },
    {
      "id": "3e5d",
      "date": "2025-11-04",
      "name": "\tFull Moon Day of Tazaungmone",
      "type": "Public",
      "recurring": false,
      "country_code": "MM",
      "region": "ALL"
    },
    {
      "id": "39e5",
      "date": "2025-11-14",
      "name": "National Day",
      "type": "Public",
      "recurring": false,
      "country_code": "MM",
      "region": "ALL"
    },
    {
      "id": "7b3d",
      "date": "2025-12-19",
      "name": "Kayin New Year Day",
      "type": "Public",
      "recurring": false,
      "country_code": "MM",
      "region": "ALL"
    },
    {
      "id": "f2b5",
      "date": "2025-12-25",
      "name": "Christmas Day",
      "type": "Public",
      "recurring": false,
      "country_code": "MM",
      "region": "ALL"
    }
  ],
  "countries": [
    {
      "id": "1",
      "Country_code": "MM",
      "Country_name": "Myanmar"
    },
    {
      "id": "2",
      "Country_code": "JP",
      "Country_name": "Japan"
    },
    {
      "id": "3",
      "Country_code": "UK",
      "Country_name": "United Kingdom"
    }
  ]
}